mcp_better_auth-0.0.1.dist-info/licenses/LICENSE
observee_agents/__init__.py
observee_agents/mcp_client.py
observee_agents/agents/__init__.py
observee_agents/agents/adaptive_swarm_manager.py
observee_agents/agents/agent.py
observee_agents/agents/agent_old.py
observee_agents/agents/base.py
observee_agents/agents/conversation.py
observee_agents/agents/streaming.py
observee_agents/agents/tool_handler.py
observee_agents/auth/__init__.py
observee_agents/auth/mcpauth.py
observee_agents/providers/__init__.py
observee_agents/providers/anthropic_provider.py
observee_agents/providers/base.py
observee_agents/providers/gemini_provider.py
observee_agents/providers/groq_provider.py
observee_agents/providers/openai_provider.py
observee_agents/search/__init__.py
observee_agents/search/base.py
observee_agents/search/bm25_filter.py
observee_agents/search/cloud_filter.py
observee_agents/search/cloud_infrastructure.py
observee_agents/search/local_embedding_filter.py
observee_agents/utils/__init__.py
observee_agents/utils/langchain_converter.py
observee_agents/utils/tool_converter.py
mcp_better_auth-0.0.1.dist-info/METADATA
mcp_better_auth-0.0.1.dist-info/WHEEL
mcp_better_auth-0.0.1.dist-info/top_level.txt
mcp_better_auth-0.0.1.dist-info/RECORD
