Metadata-Version: 2.4
Name: mcp-better-auth
Version: 0.0.1
Summary: A Python SDK for MCP tool integration with LLM providers
Author-email: Observee <contact@observee.ai>
Maintainer-email: Observee <contact@observee.ai>
License: Proprietary
Project-URL: Homepage, https://github.com/observee-ai/mcp-agent-system
Project-URL: Documentation, https://docs.observee.ai/mcp-agent-system
Project-URL: Repository, https://github.com/observee-ai/mcp-agent-system.git
Project-URL: Bug Reports, https://github.com/observee-ai/mcp-agent-system/issues
Keywords: mcp,agent,llm,anthropic,openai,gemini,tools
Classifier: Development Status :: 3 - Alpha
Classifier: Intended Audience :: Developers
Classifier: License :: Other/Proprietary License
Classifier: Operating System :: OS Independent
Classifier: Programming Language :: Python :: 3
Classifier: Programming Language :: Python :: 3.10
Classifier: Programming Language :: Python :: 3.11
Classifier: Programming Language :: Python :: 3.12
Classifier: Topic :: Software Development :: Libraries :: Python Modules
Classifier: Topic :: Scientific/Engineering :: Artificial Intelligence
Requires-Python: >=3.10
License-File: LICENSE
Requires-Dist: fastmcp
Requires-Dist: python-dotenv
Requires-Dist: anthropic
Requires-Dist: google-genai
Requires-Dist: openai
Requires-Dist: rich
Requires-Dist: bm25s
Requires-Dist: langchain
Requires-Dist: langchain-core
Requires-Dist: langchain-openai
Requires-Dist: langchain-anthropic
Requires-Dist: langchain-google-genai
Requires-Dist: jsonschema-pydantic
Requires-Dist: groq
Provides-Extra: dev
Requires-Dist: pytest>=6.0; extra == "dev"
Requires-Dist: pytest-asyncio>=0.18.0; extra == "dev"
Requires-Dist: black>=22.0; extra == "dev"
Requires-Dist: flake8>=4.0; extra == "dev"
Requires-Dist: mypy>=0.910; extra == "dev"
Requires-Dist: build; extra == "dev"
Requires-Dist: twine; extra == "dev"
Provides-Extra: embedding
Requires-Dist: fastembed>=0.1.0; extra == "embedding"
Requires-Dist: sentence-transformers; extra == "embedding"
Provides-Extra: cloud
Requires-Dist: pinecone-client>=2.0.0; extra == "cloud"
Requires-Dist: pinecone; extra == "cloud"
Dynamic: license-file
